setup.py
dsnd_probdistributions/Binomialdistribution.py
dsnd_probdistributions/Gaussiandistribution.py
dsnd_probdistributions/Generaldistribution.py
dsnd_probdistributions/__init__.py
dsnd_probdistributions.egg-info/PKG-INFO
dsnd_probdistributions.egg-info/SOURCES.txt
dsnd_probdistributions.egg-info/dependency_links.txt
dsnd_probdistributions.egg-info/not-zip-safe
dsnd_probdistributions.egg-info/top_level.txt